LICENSE.txt
MANIFEST.in
README.rst
setup.cfg
setup.py
image_generator/__init__.py
image_generator/generate_dcm.py
pylinac/__init__.py
pylinac/ct.py
pylinac/flatsym.py
pylinac/log_analyzer.py
pylinac/picketfence.py
pylinac/planar_imaging.py
pylinac/planar_imaging_master.py
pylinac/py_gui.py
pylinac/settings.py
pylinac/starshot.py
pylinac/vmat.py
pylinac/watcher_config.yml
pylinac/winston_lutz.py
pylinac/calibration/__init__.py
pylinac/calibration/tg51.py
pylinac/calibration/trs398.py
pylinac/core/__init__.py
pylinac/core/decorators.py
pylinac/core/exceptions.py
pylinac/core/geometry.py
pylinac/core/image.py
pylinac/core/io.py
pylinac/core/mask.py
pylinac/core/mtf.py
pylinac/core/pdf.py
pylinac/core/profile.py
pylinac/core/roi.py
pylinac/core/typing.py
pylinac/core/utilities.py
pylinac/core/image_generator/__init__.py
pylinac/core/image_generator/layers.py
pylinac/core/image_generator/simulators.py
pylinac/core/image_generator/utils.py
pylinac/files/Pylinac Full cropped.png
pylinac_qatrackplus.egg-info/PKG-INFO
pylinac_qatrackplus.egg-info/SOURCES.txt
pylinac_qatrackplus.egg-info/dependency_links.txt
pylinac_qatrackplus.egg-info/requires.txt
pylinac_qatrackplus.egg-info/top_level.txt