Metadata-Version: 1.1
Name: pylinac-qatrackplus
Version: 2.5.2.1
Summary: A toolkit for performing TG-142 QA-related tasks on a linear accelerator
Home-page: https://github.com/qatrackplus/pylinac
Author: James Kerns
Author-email: jkerns100@gmail.com
License: MIT
Keywords: medical physics AAPM TG142 quality assurance starshot cbct vmat dynalog starshot linac Varian Elekta
Platform: UNKNOWN
Classifier: Development Status :: 4 - Beta
Classifier: Intended Audience :: Developers
Classifier: Intended Audience :: Healthcare Industry
Classifier: Intended Audience :: Science/Research
Classifier: License :: OSI Approved :: MIT License
Classifier: Natural Language :: English
Classifier: Programming Language :: Python
Classifier: Programming Language :: Python :: 3
Classifier: Topic :: Scientific/Engineering :: Medical Science Apps.
Classifier: Topic :: Scientific/Engineering :: Image Recognition
Classifier: Topic :: Scientific/Engineering :: Physics
Classifier: Topic :: Software Development :: Libraries
